appium_oc/__init__.py
appium_oc/appium_oc.py
appium_oc/decorator.py
appium_oc-0.0.9.dist-info/LICENSE
appium_oc-0.0.9.dist-info/METADATA
appium_oc-0.0.9.dist-info/WHEEL
appium_oc-0.0.9.dist-info/top_level.txt
appium_oc-0.0.9.dist-info/RECORD
