Metadata-Version: 2.1
Name: appium-oc
Version: 0.0.9
Summary: A collection of appium-based operations
Author-email: WangYun <294961525@qq.com>
Classifier: Programming Language :: Python :: 3
Classifier: License :: OSI Approved :: MIT License
Classifier: Operating System :: OS Independent
Requires-Python: >=3.7
License-File: LICENSE
Requires-Dist: Appium-Python-Client
